LICENSE
MANIFEST.in
README.md
setup.py
doc/Makefile
doc/changelog.rst
doc/conf.py
doc/index.rst
doc/install.rst
doc/reference.rst
doc/tutorial.rst
doc/tutorialfig.py
doc/sphinxext/apigen.py
doc/sphinxext/docscrape.py
doc/sphinxext/docscrape_sphinx.py
doc/sphinxext/inheritance_diagram.py
doc/sphinxext/ipython_console_highlighting.py
doc/sphinxext/numpydoc.py
examples/C6.py
examples/SH.py
examples/minimal.py
scipydirect/__init__.py
scipydirect.egg-info/PKG-INFO
scipydirect.egg-info/SOURCES.txt
scipydirect.egg-info/dependency_links.txt
scipydirect.egg-info/requires.txt
scipydirect.egg-info/top_level.txt
scipydirect.egg-info/zip-safe
src/DIRect.f
src/DIRserial.f
src/DIRsubrout.f
src/direct.pyf
test/test_direct.py