Metadata-Version: 2.1
Name: scipydirect
Version: 1.4
Summary: Python wrapper to the DIRECT algorithm
Home-page: http://github.com/andim/scipydirect
Maintainer: Andreas Mayer
Maintainer-email: andimscience@gmail.com
License: MIT
Platform: any
Classifier: Development Status :: 5 - Production/Stable
Classifier: Programming Language :: Python
Classifier: Programming Language :: Python :: 2
Classifier: Programming Language :: Python :: 2.7
Classifier: Programming Language :: Python :: 3
Classifier: Programming Language :: Python :: 3.8
Classifier: License :: OSI Approved :: MIT License
Classifier: Intended Audience :: Science/Research
Classifier: Topic :: Scientific/Engineering
Classifier: Topic :: Scientific/Engineering :: Mathematics
Classifier: Operating System :: OS Independent
Requires: numpy
License-File: LICENSE
